vistar/__init__.py
vistar-0.0.2.dist-info/METADATA
vistar-0.0.2.dist-info/WHEEL
vistar-0.0.2.dist-info/RECORD
