Metadata-Version: 2.4
Name: vistar
Version: 0.0.2
Summary: A toolkit under development by Riemannian Vista.
Author: Marisha Singh
Requires-Python: >=3.10
